gemact/__init__.py
gemact/config.py
gemact/copulas.py
gemact/distributions.py
gemact/gemdata.py
gemact/helperfunctions.py
gemact/lossaggregation.py
gemact/lossmodel.py
gemact/lossreserve.py
gemact/sobol.py
gemact-0.1.3.dist-info/LICENSE.txt
gemact-0.1.3.dist-info/METADATA
gemact-0.1.3.dist-info/WHEEL
gemact-0.1.3.dist-info/top_level.txt
gemact-0.1.3.dist-info/RECORD
