Metadata-Version: 2.1
Name: gemact
Version: 0.1.3
Summary: A comprehensive actuarial package for non-life (re)insurance.
Home-page: https://gem-analytics.github.io/gemact/
Author: Gabriele Pittarello, Edoardo Luini, Manfred Marvin Marchione
Author-email: gabriele.pittarello@uniroma1.it
License: BSD 3-Clause
Project-URL: Source Code, https://github.com/gpitt71/gemact-code
Platform: UNKNOWN
Classifier: Development Status :: 4 - Beta
Classifier: License :: OSI Approved :: BSD License
Classifier: Programming Language :: Python
Classifier: Operating System :: Unix
Classifier: Operating System :: MacOS :: MacOS X
Classifier: Operating System :: Microsoft :: Windows
License-File: LICENSE.txt
Requires-Dist: twiggy
Requires-Dist: numpy (>=1.21.4)
Requires-Dist: matplotlib (>=3.5.0)
Requires-Dist: scipy (>=1.7.2)
